{
  "basics": {
    "name": "Alan Molina",
    "label": "Estudante | Engenharia de Controle e Automação",
    "picture": "https://alanmmolina.github.io/images/Foto - Portfolio.png",
    "email": "mmolina.alan@gmail.com",
    "phone": "+55 15 99119-7697",
    "website": "https://alanmmolina.github.io",
    "summary": "Cursando o 8º semestre de Engenharia de Controle e Automação pela Universidade Estadual Paulista Júlio de Mesquita Filho - Instituto de Ciência e Tecnologia de Sorocaba. É bolsista de Iniciação Científica pela FAPESP junto ao Grupo de Automação e Sistemas Integráveis da UNESP, realizando projeto de pesquisa e prototipagem na área de Internet das Coisas e eficiência energética. É um dos membros fundadores do grupo Mashina Robotics, participando do desenvolvimento de kits e materiais didáticos para disseminação de conhecimentos em robótica móvel. Ministra aulas particulares de reforço em Matemática e Física para alunos de Ensino Fundamental e Médio. Apaixonado por criar, encontrou na engenharia e na cultura maker uma forma de dar vida às suas ideias.",
    "location": {
      "address": "",
      "postalCode": "",
      "city": "Sorocaba",
      "countryCode": "BR",
      "region": "São Paulo"
    },
    "profiles": [
      {
        "network": "linkedin",
        "username": "alanmmolina",
        "url": "http://linkedin.com/in/alanmmolina"
      }
    ]
  },
  "interests": [
    {
      "name": "Prototipagem",
      "keywords": [
      ]
    },
    {
      "name": "Internet das Coisas",
      "keywords": [
      ]
    },
    {
      "name": "Ciência de Dados",
      "keywords": [
      ]
    }
  ],
  "skills": [
    {
      "name": "Languages and Frameworks",
      "level": "",
      "keywords": [
        "C",
        "C++",
        "Java",
        "Javascript",
        "Assembly",
        "Common Lisp"
      ]
    },
    {
      "name": "Toolsets/OS",
      "level": "",
      "keywords": [
        "MacOS",
        "Ubuntu",
        "Git/GitHub",
        "g++",
        "TI LaunchPad"
      ]
    }
  ],
  "education": [
    {
      "institution": "Universidade Estadual Paulista \"Júlio de Mesquita Filho\" - UNESP",
      "area": "Bacharelado em Engenharia de Controle e Automação",
      "studyType": "",
      "startDate": "2015",
      "endDate": "2020",
      "gpa": "",
      "courses": [
      ]
    }
  ],
  "work": [
    {
      "company": "UH Manoa Board of Publications",
      "position": "Web Developer",
      "website": "",
      "startDate": "2015-08-01",
      "endDate": "Present",
      "summary": "Head of online presence for Ka Leo",
      "highlights": [
        "Maintain, update, and oversee official college newspaper website",
        "Drive, design and build student-community projects for UH Manoa"
      ]
    },
    {
      "company": "UH Information Technology Services",
      "position": "Help Desk Consultant",
      "website": "http://www.hawaii.edu/its/",
      "startDate": "2015-01-01",
      "endDate": "2016-03-15",
      "summary": "",
      "highlights": [
        "Troubleshoot software, hardware and networking issues over the phone",
        "Answer phone and email responses to the ITS Help Desk"
      ]
    }
  ],
  "volunteer": [
    {
      "organization": "Center for Renewable Energy and Island Sustainability",
      "website": "http://manoa.hawaii.edu/reis",
      "position": "Software Developer",
      "startDate": "2016-01-01",
      "endDate": "Present",
      "summary": "Lead developer for weather sensing project",
      "highlights": [
        "Design firmware for distributed weather sensor network",
        "Maintain custom data collection and storage infrastructure"
      ]
    },
    {
      "organization": "",
      "website": "",
      "position": "Professional organization involvement",
      "startDate": "",
      "endDate": "",
      "summary": "",
      "highlights": [
        "Chair, ACM Manoa, 2016-Present",
        "Member, IEEE Student Branch, 2014-Present",
        "Webmaster/IT Officer, IEEE Student Branch, UH Manoa, 2012-2013"
      ]
    }
  ],
  "awards": [
    {
      "title": "B+ Scholarship",
      "date": "2013-Present",
      "awarder": "State of Hawaii",
      "summary": "Scholarships awarded to incoming freshmen and continuing students who complete a rigorous high school curriculum with a minimum overall GPA of 3.0 at a Hawai'i public school."
    },
    {
      "title": "First place",
      "date": "2015",
      "awarder": "University of Hawaii Micromouse Competition",
      "summary": "My team won first place in 2015.  See my portfolio site for more details."
    }
  ],
  "references": [
    {
      "name": "Available upon request",
      "reference": ""
    }
  ]
}
